{"posts": [{"author": "Adi", "difficultyRank": 1, "generalRank": 4, "semester": "202001", "text": "שם המרצה: בן ציון מיטל\nחוות דעת - הרצאות: משעמם מאוד, הסמסטר היה בזום ולכן המרצה פשוט העלה וידיאו של מצגת עם הקלטות קוליות והסברים שלו עליה.\n\nשם המתרגל/ת: אין\nחוות דעת - תרגולים: אין\n\nשעורי הבית: 3-4 גיליונות ש\"ב, יש רפרנסים בדרייב. גיליונות לא קשים בכלל.\n\nהמבחן: אין מבחן, יש פרויקט סוף שמשתנה מסמסטר לסמסטר. פרויקט של הרבה עמודים אבל לא דורש למידה במהלך הסמסטר אלא רק עבודה נקודתית על הפרויקט.\n\nהשורה התחתונה: קורס מומלץ לנקודות זכות עם מעט השקעה. מי שרוצה יכול גם ללמוד מהקורס ולהעשיר את הידע. ציונים בפרויקט אקראיים ונעים בין 85 ל92 בערך.", "timestamp": 1617521271965}]}