{"posts": [{"author": ".", "difficultyRank": 4, "generalRank": 2, "semester": "202301", "text": "שם המרצה: פנחס בר יוסף\nחוות דעת - הרצאות: יש 5 נק בונוס לציון הסופי אם נוכחים בהרצאות (וגם בתרגולים). אני לא ממש הקשבתי אז לא יודעת להגיד כמה זה תרם.\n\nשם המתרגל/ת:  עמית אשכנזי\nחוות דעת - תרגולים: אחלה מתרגל, בגדול הכל דיי מובן מדפי התרגולים המודפסים, עמית עבר על הדברים בצורה מובנת. מומלץ להדפיס את הדפים כדי לכתוב רק הערות ולהיות מרוכזים בפתרון התרגילים עצמם. התרגולים מאוד עוזרים להבנתי ולדעתי חשובים.\n\nשעורי הבית: לנו היו 5 גיליונות ש\"ב, חלקם דומים לקורס אלמנטים סופיים אחר שיש בפקולטה בלימודי תואר ראשון. בהמשך הקורס התרגילים כבר שונים לחלוטין. תרגילי בית מולקדים בלבד ולא מאוד קלים אבל לא מאוד קשים, דיי מבוסס על התרגולים. כן דורש לא מעט מטלב אז יותר קל למי שטוב ומכיר את התוכנה. שני הגיליונות האחרונים עוזרים להניע את הפרויקט המסכם אז זו עבודה שלא עושים לחינם.\n\nהמבחן: אפשר או לגשת למבחן מסכם כרגיל או לעשות פרויקט מסכם. הפרויקט זה משאבת זמן ענקית, לדעתי לוקח הרבה יותר שעות עבודה מאשר ללמוד למבחן. כן מורגש שזה מלמד את החומר בצורה טובה ולי אישית היה יותר נוח להשקיע בפרויקט מאשר לגשת למבחן. אחרי שמגישים את הפרויקט (שגם הוא מבוצע במטלב) יש הגנה על הפרויקט. אנחנו קיבלנו שאלון אישי עם שאלות על הפרויקט הספציפי שביצענו והיינו צריכים להשיב במחברת הבחינה.\n\nהשורה התחתונה: אם זה לתואר ראשון אז יש קורסי אלמנטים יותר קלים מזה... מעבר לזה הקורס הוא קצת משאבת זמן אבל אם לומדים לאורך הסמסטר אפשר להסתדר עם החומר ועם שיעורי הבית. לא מומלץ בתור קורס בחירה, מומלץ לקחת רק אם זה קורס חובה.", "timestamp": 1715190835947}]}