{"posts": [{"author": ".", "difficultyRank": 2, "generalRank": 3, "semester": "202301", "text": "שם המרצה: בני נתן\nחוות דעת - הרצאות: בני מעביר את ההרצאות בצורה די משעממת. חלק ניכר מהזמן הוא מקריא משוואות מתוך המצגת ואין המון ערך מוסף להרצאה עצמה.\n\nשעורי הבית: מרופרנסים, אך ניתן לפתור אותם בקלות באופן עצמאי. לרוב דורשים לצייר גרפים או לפתור משוואות נומרית, מה שלא תורם כמעט בכלל להכנה למבחן.\n\nהמבחן: מבחן בעל פה של כמה דקות. השאלות סך הכל חוזרות על עצמן אז שווה להירשם לבחינה יחסית מאוחרת כדי לשמוע את השאלות שהוא שאל את הסטודנטים הקודמים. החומר לא קשה אבל בני נוטה לשאול על דברים מאוד נקודתיים ככה שאפשר ליפול בקלות.\n\nהשורה התחתונה: הרעיון הכללי נחמד, לקורס עצמו פחות התחברתי.", "timestamp": 1713956530379}, {"author": "xuph", "difficultyRank": 2, "generalRank": 3, "semester": "202301", "text": "שם המרצה: בני נתן\nחוות דעת - הרצאות: \nבני אוהב לספר סיפורים מעניינים בהרצאות כמו הפעם ההיא שעצר אותו שוטר ביוון אבל הוא דיבר איתו וצחק איתו אז הוא נתן לו ללכת ולא עשה לו כלום. או על הרגשות שלו כלפי העם הטורקי. או על איך שהוא הצית את הבן של השכנה כשהוא היה קטן כי הוא פירומן. או על מערכת היחסים המורכבת שלו עם סבתא. בקיצור, כל דבר חוץ ממגח. לא שאני לא ממליץ ללכת - סיפורים מרתקים ונהנתי מכל רגע.\n\nשם המתרגל/ת: דוד קסטנדה\nחוות דעת - תרגולים: לא היה תרגולים באמת\n\nשעורי הבית: \n8 גליונות מרופרנסים יחסית ולא קשים מדי. חשוב לצרף קוד - מורידים על זה ניקוד ומשום מה זה לא היה מודגש מספיק בהנחיות לש\"ב. \n\nהמבחן: \nמבחן בעל פה - 8 דקות בזום אחד על אחד עם בני בכבודו ובעצמו, הוא קוטע ורץ על החומר כשהוא רואה שאתם מבינים - לבוא חדים על החומר של ההרצאות ויהיה בסדר.\n\nהשורה התחתונה: \nקורס קל יחסית עם ממוצע גבוה. עם זאת הוא לא באמת מלמד את הנושא הסופר קול של מגח כמו שהייתי רוצה.", "timestamp": 1715759776703}]}