{"posts": [{"author": "עדי", "difficultyRank": 1, "generalRank": 4, "semester": "202001", "text": "שם המרצה: שרה זליג\n\nחוות דעת - הרצאות: ההרצאות מעניינות אבל ארוכות וקשה לשמור על ריכוז כל הזמן. יש אפשרות בתחילת הסמסטר להעלות בפני המרצה מחלות או גנים שמעניינים אותנו והיא מנסה לשלב את זה בהרצאות שלה. שרה מקסימה! אם היא לא יודעת תשובה לשאלה היא בודקת ומפרסמת תשובה עד להרצאה הבאה.\n\nתרגולים: אין\nשעורי הבית: אין", "timestamp": 1612278652323}, {"author": "--", "difficultyRank": 1, "generalRank": 3, "semester": "202101", "text": "שם המרצה: שרה זליג\nחוות דעת - הרצאות: שרה חביבה, מעבירה את החומר עם מוטיבציה ללמד ולענות על שאלות ולעורר השתתפות. אבל מעט מונוטונית והשעה השלישית לרוב דיי מעייפת.\n\nשעורי הבית: אין\n\nהמבחן: הייתה הערכה חלופית בתצורת עבודה. המון השקעה, 100 אחוז מהציון. שאלות נוסחו באופן מעורפל והיא לא קיבלה תשובות אחרות ממה שהיא ניסחה בפרסום התשובון. בפתיחת מחברות היא לא הראתה הרבה גמישות והתקבלו מעט ערעורים. לכולם ניתנה נקודה אחת בונוס\\פקטור אחרי פתיחת המחברות.\n\nהשורה התחתונה: אין עומס בכלל במהלך הסמסטר, אם יש עבודה בסוף- כמות ההשקעה דיי גבוהה והציונים לא היו גבוהים ביחס לקורס בחירה.", "timestamp": 1650821248274}]}